{
  "db_name": "PostgreSQL",
  "query": "\n            SELECT tag.id, tag.description\n            FROM tag\n            WHERE tag.account_id = $1;\n        ",
  "describe": {
    "columns": [
      {
        "ordinal": 0,
        "name": "id",
        "type_info": "Uuid"
      },
      {
        "ordinal": 1,
        "name": "description",
        "type_info": "Text"
      }
    ],
    "parameters": {
      "Left": [
        "Uuid"
      ]
    },
    "nullable": [
      false,
      false
    ]
  },
  "hash": "99f848f59f3fe4bc533e95921d3b46b90b2ec18fa4b90373b5b3b2e5d6ef8c91"
}
